MANIFEST.in
README.rst
setup.py
aliyun_python_sdk_petadata.egg-info/PKG-INFO
aliyun_python_sdk_petadata.egg-info/SOURCES.txt
aliyun_python_sdk_petadata.egg-info/dependency_links.txt
aliyun_python_sdk_petadata.egg-info/requires.txt
aliyun_python_sdk_petadata.egg-info/top_level.txt
aliyunsdkpetadata/__init__.py
aliyunsdkpetadata/request/__init__.py
aliyunsdkpetadata/request/v20160101/AllocateInstancePublicConnectionRequest.py
aliyunsdkpetadata/request/v20160101/CreateAccountRequest.py
aliyunsdkpetadata/request/v20160101/CreateDatabaseBackupRequest.py
aliyunsdkpetadata/request/v20160101/CreateDatabaseRequest.py
aliyunsdkpetadata/request/v20160101/CreateInstanceRequest.py
aliyunsdkpetadata/request/v20160101/DeleteAccountRequest.py
aliyunsdkpetadata/request/v20160101/DeleteDatabaseRequest.py
aliyunsdkpetadata/request/v20160101/DeleteInstanceRequest.py
aliyunsdkpetadata/request/v20160101/DescribeAccountsRequest.py
aliyunsdkpetadata/request/v20160101/DescribeBackupPolicyRequest.py
aliyunsdkpetadata/request/v20160101/DescribeDatabaseBackupRequest.py
aliyunsdkpetadata/request/v20160101/DescribeDatabasePartitionsRequest.py
aliyunsdkpetadata/request/v20160101/DescribeDatabasePerformanceRequest.py
aliyunsdkpetadata/request/v20160101/DescribeDatabaseResourceUsageRequest.py
aliyunsdkpetadata/request/v20160101/DescribeDatabasesRequest.py
aliyunsdkpetadata/request/v20160101/DescribeInstanceInfoRequest.py
aliyunsdkpetadata/request/v20160101/DescribeInstancePerformanceRequest.py
aliyunsdkpetadata/request/v20160101/DescribeInstanceResourceUsageRequest.py
aliyunsdkpetadata/request/v20160101/DescribeInstancesRequest.py
aliyunsdkpetadata/request/v20160101/DescribeMonitorItemsRequest.py
aliyunsdkpetadata/request/v20160101/DescribePriceRequest.py
aliyunsdkpetadata/request/v20160101/DescribeRegionsRequest.py
aliyunsdkpetadata/request/v20160101/DescribeSecurityIPsRequest.py
aliyunsdkpetadata/request/v20160101/DescribeTaskStatusRequest.py
aliyunsdkpetadata/request/v20160101/DescribeTasksRequest.py
aliyunsdkpetadata/request/v20160101/DescribeUserInfoRequest.py
aliyunsdkpetadata/request/v20160101/GrantAccountPrivilegeRequest.py
aliyunsdkpetadata/request/v20160101/ListTagResourcesRequest.py
